<?xml version="1.0" ?>
<mosinstall type="component">
    <name>JoomlaStats</name>
    <creationDate>26 Nov 2006</creationDate>
    <author>JoomlaStats Team</author>
    <copyright>Copyright (C) 2004-2006 JoomlaStats. All rights reserved.</copyright>
    <authorEmail>info@JoomlaStats.org</authorEmail>
    <authorUrl>www.JoomlaStats.org</authorUrl>
    <version>2.1.5</version>
    <description>JoomlaStats statistiques pour Joomla</description>
    
    <files>
        <filename>index.html</filename>
        <filename>joomlastats.html.php</filename>
        <filename>joomlastats.inc.php</filename>
        <filename>joomlastats.php</filename>		
    </files>
    
    <images>
	<filename>images/index.html</filename>
	<filename>images/joomlastats.png</filename>
	
	<filename>images/tld/index.html</filename>
	<filename>images/tld/ac.png</filename>
	<filename>images/tld/ad.png</filename>
	<filename>images/tld/ae.png</filename>
	<filename>images/tld/aero.png</filename>
	<filename>images/tld/af.png</filename>
	<filename>images/tld/ag.png</filename>
	<filename>images/tld/ai.png</filename>
	<filename>images/tld/al.png</filename>
	<filename>images/tld/am.png</filename>
	<filename>images/tld/an.png</filename>
	<filename>images/tld/ao.png</filename>
	<filename>images/tld/aq.png</filename>
	<filename>images/tld/ar.png</filename>
	<filename>images/tld/arpa.png</filename>
	<filename>images/tld/as.png</filename>
	<filename>images/tld/at.png</filename>
	<filename>images/tld/au.png</filename>
	<filename>images/tld/aw.png</filename>
	<filename>images/tld/ax.png</filename>	
	<filename>images/tld/az.png</filename>
	<filename>images/tld/ba.png</filename>
	<filename>images/tld/bb.png</filename>
	<filename>images/tld/bd.png</filename>
	<filename>images/tld/be.png</filename>
	<filename>images/tld/bf.png</filename>
	<filename>images/tld/bg.png</filename>
	<filename>images/tld/bh.png</filename>
	<filename>images/tld/bi.png</filename>
	<filename>images/tld/biz.png</filename>
	<filename>images/tld/bj.png</filename>
	<filename>images/tld/bm.png</filename>
	<filename>images/tld/bn.png</filename>
	<filename>images/tld/bo.png</filename>
	<filename>images/tld/br.png</filename>
	<filename>images/tld/bs.png</filename>
	<filename>images/tld/bt.png</filename>
	<filename>images/tld/bv.png</filename>
	<filename>images/tld/bw.png</filename>
	<filename>images/tld/by.png</filename>
	<filename>images/tld/bz.png</filename>
	<filename>images/tld/ca.png</filename>
	<filename>images/tld/cat.png</filename>
	<filename>images/tld/cc.png</filename>
	<filename>images/tld/cd.png</filename>
	<filename>images/tld/cf.png</filename>
	<filename>images/tld/cg.png</filename>
	<filename>images/tld/ch.png</filename>
	<filename>images/tld/ci.png</filename>
	<filename>images/tld/ck.png</filename>
	<filename>images/tld/cl.png</filename>
	<filename>images/tld/cm.png</filename>
	<filename>images/tld/cn.png</filename>
	<filename>images/tld/co.png</filename>
	<filename>images/tld/com.png</filename>
	<filename>images/tld/coop.png</filename>
	<filename>images/tld/cr.png</filename>
	<filename>images/tld/cs.png</filename>
	<filename>images/tld/cu.png</filename>
	<filename>images/tld/cv.png</filename>
	<filename>images/tld/cx.png</filename>
	<filename>images/tld/cy.png</filename>
	<filename>images/tld/cz.png</filename>
	<filename>images/tld/de.png</filename>
	<filename>images/tld/dj.png</filename>
	<filename>images/tld/dk.png</filename>
	<filename>images/tld/dm.png</filename>
	<filename>images/tld/do.png</filename>
	<filename>images/tld/dz.png</filename>
	<filename>images/tld/ec.png</filename>
	<filename>images/tld/edu.png</filename>
	<filename>images/tld/ee.png</filename>
	<filename>images/tld/eg.png</filename>
	<filename>images/tld/eh.png</filename>
	<filename>images/tld/er.png</filename>
	<filename>images/tld/es.png</filename>
	<filename>images/tld/et.png</filename>
	<filename>images/tld/eu.png</filename>
	<filename>images/tld/fi.png</filename>
	<filename>images/tld/fj.png</filename>
	<filename>images/tld/fk.png</filename>
	<filename>images/tld/fm.png</filename>
	<filename>images/tld/fo.png</filename>
	<filename>images/tld/fr.png</filename>
	<filename>images/tld/ga.png</filename>
	<filename>images/tld/gb.png</filename>
	<filename>images/tld/gd.png</filename>
	<filename>images/tld/ge.png</filename>
	<filename>images/tld/gf.png</filename>
	<filename>images/tld/gg.png</filename>	
	<filename>images/tld/gh.png</filename>
	<filename>images/tld/gi.png</filename>
	<filename>images/tld/gl.png</filename>
	<filename>images/tld/gm.png</filename>
	<filename>images/tld/gn.png</filename>
	<filename>images/tld/gov.png</filename>
	<filename>images/tld/gp.png</filename>
	<filename>images/tld/gq.png</filename>
	<filename>images/tld/gr.png</filename>
	<filename>images/tld/gs.png</filename>
	<filename>images/tld/gt.png</filename>
	<filename>images/tld/gu.png</filename>
	<filename>images/tld/gw.png</filename>
	<filename>images/tld/gy.png</filename>
	<filename>images/tld/hk.png</filename>
	<filename>images/tld/hm.png</filename>
	<filename>images/tld/hn.png</filename>
	<filename>images/tld/hr.png</filename>
	<filename>images/tld/ht.png</filename>
	<filename>images/tld/hu.png</filename>
	<filename>images/tld/id.png</filename>
	<filename>images/tld/ie.png</filename>
	<filename>images/tld/il.png</filename>
	<filename>images/tld/im.png</filename>
	<filename>images/tld/in.png</filename>
	<filename>images/tld/info.png</filename>
	<filename>images/tld/int.png</filename>
	<filename>images/tld/io.png</filename>
	<filename>images/tld/iq.png</filename>
	<filename>images/tld/ir.png</filename>
	<filename>images/tld/is.png</filename>
	<filename>images/tld/it.png</filename>
	<filename>images/tld/je.png</filename>
	<filename>images/tld/jm.png</filename>
	<filename>images/tld/jo.png</filename>
	<filename>images/tld/jobs.png</filename>
	<filename>images/tld/jp.png</filename>
	<filename>images/tld/ke.png</filename>
	<filename>images/tld/kg.png</filename>
	<filename>images/tld/kh.png</filename>
	<filename>images/tld/ki.png</filename>
	<filename>images/tld/km.png</filename>
	<filename>images/tld/kn.png</filename>
	<filename>images/tld/kp.png</filename>
	<filename>images/tld/kr.png</filename>
	<filename>images/tld/kw.png</filename>
	<filename>images/tld/ky.png</filename>
	<filename>images/tld/kz.png</filename>
	<filename>images/tld/la.png</filename>
	<filename>images/tld/lb.png</filename>
	<filename>images/tld/lc.png</filename>
	<filename>images/tld/li.png</filename>
	<filename>images/tld/lk.png</filename>
	<filename>images/tld/lr.png</filename>
	<filename>images/tld/ls.png</filename>
	<filename>images/tld/lt.png</filename>
	<filename>images/tld/lu.png</filename>
	<filename>images/tld/lv.png</filename>
	<filename>images/tld/ly.png</filename>
	<filename>images/tld/ma.png</filename>
	<filename>images/tld/mc.png</filename>
	<filename>images/tld/md.png</filename>
	<filename>images/tld/mg.png</filename>
	<filename>images/tld/mh.png</filename>
	<filename>images/tld/mil.png</filename>
	<filename>images/tld/mk.png</filename>
	<filename>images/tld/ml.png</filename>
	<filename>images/tld/mm.png</filename>
	<filename>images/tld/mn.png</filename>
	<filename>images/tld/mo.png</filename>
	<filename>images/tld/mobi.png</filename>
	<filename>images/tld/mp.png</filename>	
	<filename>images/tld/mq.png</filename>
	<filename>images/tld/mr.png</filename>
	<filename>images/tld/ms.png</filename>
	<filename>images/tld/mt.png</filename>
	<filename>images/tld/mu.png</filename>
	<filename>images/tld/museum.png</filename>
	<filename>images/tld/mv.png</filename>
	<filename>images/tld/mw.png</filename>
	<filename>images/tld/mx.png</filename>
	<filename>images/tld/my.png</filename>
	<filename>images/tld/mz.png</filename>
	<filename>images/tld/na.png</filename>
	<filename>images/tld/name.png</filename>
	<filename>images/tld/nc.png</filename>
	<filename>images/tld/ne.png</filename>
	<filename>images/tld/net.png</filename>
	<filename>images/tld/nf.png</filename>
	<filename>images/tld/ng.png</filename>
	<filename>images/tld/ni.png</filename>
	<filename>images/tld/nl.png</filename>
	<filename>images/tld/no.png</filename>
	<filename>images/tld/np.png</filename>
	<filename>images/tld/nr.png</filename>
	<filename>images/tld/nt.png</filename>
	<filename>images/tld/nu.png</filename>
	<filename>images/tld/nz.png</filename>
	<filename>images/tld/om.png</filename>
	<filename>images/tld/org.png</filename>
	<filename>images/tld/pa.png</filename>
	<filename>images/tld/pe.png</filename>
	<filename>images/tld/pf.png</filename>
	<filename>images/tld/pg.png</filename>
	<filename>images/tld/ph.png</filename>
	<filename>images/tld/pk.png</filename>
	<filename>images/tld/pl.png</filename>
	<filename>images/tld/pm.png</filename>
	<filename>images/tld/pn.png</filename>
	<filename>images/tld/pr.png</filename>
	<filename>images/tld/pro.png</filename>
	<filename>images/tld/ps.png</filename>
	<filename>images/tld/pt.png</filename>
	<filename>images/tld/pw.png</filename>
	<filename>images/tld/py.png</filename>
	<filename>images/tld/qa.png</filename>
	<filename>images/tld/re.png</filename>
	<filename>images/tld/ro.png</filename>
	<filename>images/tld/ru.png</filename>
	<filename>images/tld/rw.png</filename>
	<filename>images/tld/sa.png</filename>
	<filename>images/tld/sb.png</filename>
	<filename>images/tld/sc.png</filename>
	<filename>images/tld/sd.png</filename>
	<filename>images/tld/se.png</filename>
	<filename>images/tld/sg.png</filename>
	<filename>images/tld/sh.png</filename>
	<filename>images/tld/si.png</filename>
	<filename>images/tld/sj.png</filename>
	<filename>images/tld/sk.png</filename>
	<filename>images/tld/sl.png</filename>
	<filename>images/tld/sm.png</filename>
	<filename>images/tld/sn.png</filename>
	<filename>images/tld/so.png</filename>
	<filename>images/tld/sr.png</filename>
	<filename>images/tld/st.png</filename>
	<filename>images/tld/su.png</filename>
	<filename>images/tld/sv.png</filename>
	<filename>images/tld/sy.png</filename>
	<filename>images/tld/sz.png</filename>
	<filename>images/tld/tc.png</filename>
	<filename>images/tld/td.png</filename>
	<filename>images/tld/tf.png</filename>
	<filename>images/tld/tg.png</filename>
	<filename>images/tld/th.png</filename>
	<filename>images/tld/tj.png</filename>
	<filename>images/tld/tk.png</filename>
	<filename>images/tld/tl.png</filename>
	<filename>images/tld/tm.png</filename>
	<filename>images/tld/tn.png</filename>
	<filename>images/tld/to.png</filename>
	<filename>images/tld/tp.png</filename>
	<filename>images/tld/tr.png</filename>
	<filename>images/tld/travel.png</filename>
	<filename>images/tld/tt.png</filename>	
	<filename>images/tld/tv.png</filename>
	<filename>images/tld/tw.png</filename>
	<filename>images/tld/tz.png</filename>
	<filename>images/tld/ua.png</filename>
	<filename>images/tld/ug.png</filename>
	<filename>images/tld/uk.png</filename>
	<filename>images/tld/um.png</filename>
	<filename>images/tld/unknown.png</filename>
	<filename>images/tld/us.png</filename>
	<filename>images/tld/uy.png</filename>
	<filename>images/tld/uz.png</filename>
	<filename>images/tld/va.png</filename>
	<filename>images/tld/vc.png</filename>
	<filename>images/tld/ve.png</filename>
	<filename>images/tld/vg.png</filename>
	<filename>images/tld/vi.png</filename>
	<filename>images/tld/vn.png</filename>
	<filename>images/tld/vu.png</filename>
	<filename>images/tld/wf.png</filename>
	<filename>images/tld/ws.png</filename>
	<filename>images/tld/ye.png</filename>
	<filename>images/tld/yt.png</filename>
	<filename>images/tld/yu.png</filename>
	<filename>images/tld/za.png</filename>
	<filename>images/tld/zm.png</filename>
	<filename>images/tld/zw.png</filename>
	
    </images>
	<installfile>install.com_joomlastats.php</installfile>
	<uninstallfile>uninstall.com_joomlastats.php</uninstallfile>
    <administration>
         <menu task="stats">JoomlaStats</menu>
	<files>
		<filename>index.html</filename>
		<filename>admin.joomlastats.html.php</filename>
		<filename>admin.joomlastats.php</filename>
		<filename>toolbar.joomlastats.html.php</filename>
		<filename>toolbar.joomlastats.php</filename>
		<filename>language/index.html</filename>	
		<filename>language/ch.ini.php</filename>
		<filename>language/cz.ini.php</filename>
		<filename>language/de.ini.php</filename>
		<filename>language/dk.ini.php</filename>
		<filename>language/en.ini.php</filename>
		<filename>language/es.ini.php</filename>		
		<filename>language/fr.ini.php</filename>
		<filename>language/it.ini.php</filename>
		<filename>language/lt.ini.php</filename>
		<filename>language/nl.ini.php</filename>
		<filename>language/no.ini.php</filename>
		<filename>language/pl.ini.php</filename>
		<filename>language/pt.ini.php</filename>
		<filename>language/ru.ini.php</filename>
		<filename>language/se.ini.php</filename>
		<filename>language/tr.ini.php</filename>		
	</files>
	<images>
		<filename>images/index.html</filename>	
		<filename>images/bar-.gif</filename>
		<filename>images/bar+.gif</filename>
		<filename>images/config.png</filename>
		<filename>images/home.png</filename>
		<filename>images/joomlastats_icon.png</filename>		
	</images>
    </administration>
</mosinstall>